mendeley2biblatex/__init__.py
mendeley2biblatex/bib_entry.py
mendeley2biblatex/library_converter.py
mendeley2biblatex-0.1.8.dist-info/DESCRIPTION.rst
mendeley2biblatex-0.1.8.dist-info/METADATA
mendeley2biblatex-0.1.8.dist-info/RECORD
mendeley2biblatex-0.1.8.dist-info/WHEEL
mendeley2biblatex-0.1.8.dist-info/entry_points.txt
mendeley2biblatex-0.1.8.dist-info/metadata.json
mendeley2biblatex-0.1.8.dist-info/top_level.txt
