Metadata-Version: 2.0
Name: mendeley2biblatex
Version: 0.1.8
Summary: A tool to convert your Mendeley to a biblatex library
Home-page: https://github.com/lioman/mendeley2biblatex
Author: Lioman
Author-email: dev@lioman.de
License: GNU General Public License v3 or later (GPLv3+)
Keywords: mendeley latex biblatex bibtex biber
Platform: UNKNOWN
Classifier: Development Status :: 4 - Beta
Classifier: Intended Audience :: Science/Research
Classifier: Topic :: Utilities
Classifier: Topic :: Scientific/Engineering
Classifier: Topic :: Text Processing :: General
Classifier: Environment :: Console
Classifier: License :: OSI Approved :: GNU General Public License v3 or later (GPLv3+)
Classifier: Programming Language :: Python :: 3
Classifier: Programming Language :: Python :: 3.3
Classifier: Programming Language :: Python :: 3.4
Classifier: Programming Language :: Python :: 3.5
